controlUnit.v
module controlUnit(inCode,outCode,clk);
	input[5:0] inCode;
	input clk;
	output[8:0] outCode; 
	reg[8:0] result; 
//0011100000
	always @(posedge clk)
	begin
		case(inCode)
			6'b000000: result<=9'b100100010;
			6'b100011: result<=9'b011110000;
			6'b101011: result<=9'b010001000;
			6'b000100: result<=9'b000000101;
			default: result<=9'b000000000;
		endcase
	end

	assign outCode = result;

endmodule

controlUnit_test.v
`include"controlUnit.v"
//module controlUnit(inCode,outCode,clk);
module controlUnit_test();
	reg clk;
	reg[5:0] inCode;
	wire[8:0] outCode;

	controlUnit c(.inCode(inCode),.outCode(outCode),.clk(clk));

	initial 
	begin
		$dumpfile("cu.vcd");
		$dumpvars;
		clk<=0;
		#10 inCode=6'b000000;
		#10 inCode<=6'b101011;
		#10 inCode=6'b100011;
		#10 $finish;
	end

	always 
	begin
		#4 clk=~clk;
	end

endmodule

cu.vcd
$date
	Mon May 16 15:25:33 2016
$end
$version
	Icarus Verilog
$end
$timescale
	1s
$end
$scope module controlUnit_test $end
$var wire 9 ! outCode [8:0] $end
$var reg 1 " clk $end
$var reg 6 # inCode [5:0] $end
$scope module c $end
$var wire 1 $ clk $end
$var wire 6 % inCode [5:0] $end
$var wire 9 & outCode [8:0] $end
$var reg 9 ' result [8:0] $end
$upscope $end
$upscope $end
$enddefinitions $end
#0
$dumpvars
bx '
bx &
bx %
0$
bx #
0"
bx !
$end
#4
b0 '
b0 !
b0 &
1"
1$
#8
0"
0$
#10
b0 #
b0 %
#12
b100100010 '
b100100010 !
b100100010 &
1"
1$
#16
0"
0$
#20
b101011 #
b101011 %
1"
1$
#24
0"
0$
#28
b10001000 '
b10001000 !
b10001000 &
1"
1$
#30
b100011 #
b100011 %
#32
0"
0$
#36
b11110000 '
b11110000 !
b11110000 &
1"
1$
