muxtwo_32.v
//32???????
module muxtwo_32(in1,in2,sl,out);
  input[31:0] in1;
  input[31:0] in2;  
  input sl;   //????????
  output[31:0] out;
  
  assign out=(sl==0)?in1:in2;
  
endmodule

DM.v
module DM(inAddr,writeData,memRead,memWrite,outData,clk);
	input[31:0] inAddr;
	input[31:0] writeData;
	input memRead;
	input memWrite;
	output[31:0] outData;
	input clk;

	reg[7:0] mem[1023:0];

	initial begin
		$readmemh("DMData.data",mem);
	end

	always @(posedge clk) begin
		if(memWrite) begin
			mem[inAddr]=writeData[7:0];
			mem[inAddr+1]=writeData[15:8];
			mem[inAddr+2]=writeData[23:15];
			mem[inAddr+3]=writeData[31:24];
		end
		else;
	end

	assign outData = (memRead==1)?{mem[inAddr+3],mem[inAddr+2],mem[inAddr+1],mem[inAddr]}:0;

endmodule

ALU.v
module ALU(in1,in2,ctrl,out);
  input[31:0] in1;
  input[31:0] in2;
  input[3:0] ctrl;
  input clk;
  reg[31:0] result;
  output[31:0] out;
  
  initial
  begin
    result=0;
  end
  
  
  always @(in1 or in2 or ctrl)
  begin
    case(ctrl)
    4'b0000:  result<=in1&in2;
    4'b0001:  result<=in1||in2;
    4'b0010:  result<=in1+in2;
    4'b0110:  result<=in1-in2;
    4'b0111:  result<=(in1<in2)?1:0;
    4'b1100:  result<=!(in1||in2);
    default:  result<=0;
  endcase
  end
  
  assign out=result;
  
  
endmodule

ALUControl.v
module ALUControl(func,aluop,aluctrl,clk);
	input[5:0] func;
	input[1:0] aluop;
	input clk;
	output[3:0] aluctrl;

	reg[3:0] aluctrl;

	always @(posedge clk) begin
		if(aluop==2'b00)
			aluctrl<=4'b0010;
		else if(aluop==2'b01)
			aluctrl<=4'b0110;
		else if(aluop==2'b10)
			begin
				case(func)
					6'b100000: aluctrl<=4'b0010;
					6'b100010: aluctrl<=4'b0110;
					6'b100100: aluctrl<=4'b0000;
					6'b100101: aluctrl<=4'b0001;
					6'b101010: aluctrl<=4'b0111;
					default: aluctrl<=4'b0000;
				endcase
			end
		else 
			aluctrl<=0;
	end

endmodule

signExt.v
module signExt(in1,out);
	input[15:0] in1;
	output[31:0] out;
	wire[15:0] temp;

	assign temp=in1[15]==0?16'h0000:16'hffff;
	assign out ={temp[15:0],in1[15:0]} ;


endmodule

RegHeap.v
module RegHeap(readReg1,readReg2,writeReg,regWrite,writeData,reg1Data,reg2Data,clk);
  input[4:0] readReg1;
  input[4:0] readReg2;
  input[4:0] writeReg;//
  input regWrite;//
  input[31:0] writeData;
  input clk;
  output[31:0] reg1Data;
  output[31:0] reg2Data;
  
  reg[31:0] mem[31:0];//????

  initial
  begin
    $readmemh("regHeapData.data",mem);
  end
  
  always @(posedge clk or writeData)
  begin
    if(regWrite)mem[writeReg]<=writeData;  
  end
  
   assign reg1Data=mem[readReg1];
   assign reg2Data=mem[readReg2];
  
endmodule

muxtwo_4.v
//????????????????????????????????????
module muxtwo_4(in1,in2,sl,out);
  input[4:0] in1;
  input[4:0] in2;  
  input sl;   //
  output[4:0] out;
  
  assign out=(sl==0)?in1:in2;
  
endmodule

controlUnit.v
module controlUnit(inCode,outCode);
	input[5:0] inCode;
	input clk;
	output[8:0] outCode; 
	reg[8:0] result; 
//0011100000
	always @(inCode)
	begin
		case(inCode)
			6'b000000: result<=9'b100100010;
			6'b100011: result<=9'b011110000;
			6'b101011: result<=9'b010001000;
			6'b000100: result<=9'b000000101;
			default: result<=9'b000000000;
		endcase
	end

	assign outCode = result;

endmodule

IM.v
module IM #(parameter WIDTH=32)(inAddr,outContent);
  reg[7:0] mem[16383:0];//256?32?????????????
  input[WIDTH-1:0] inAddr;//????????
  output[WIDTH-1:0] outContent;//??????
  
  
  
  initial
  begin
    $readmemh("overflow.data",mem);
  end
  assign outContent={mem[inAddr+3],mem[inAddr+2],mem[inAddr+1],mem[inAddr]};
  
  
endmodule

PC.v
module PC #(parameter WIDTH=32) (inAddr,outAddr,clk);
  input[WIDTH-1:0] inAddr;
  output[WIDTH-1:0] outAddr;
  reg[WIDTH-1:0] outAddr;
  input clk;
  reg[WIDTH-1:0] con;

  
  initial
  begin
    con<=0;
  end
  
  always @(posedge clk)
  begin
    outAddr<=inAddr;
  end
  
  //assign outAddr=con;
endmodule

testBench.v
`include"PC.v"
`include"IM.v"
`include"controlUnit.v"
`include"RegHeap.v"
`include"muxtwo_4.v"
`include"signExt.v"
`include"muxtwo_32.v"
`include"ALUControl.v"
`include"ALU.v"
`include"DM.v"
module testBench();
	reg clk;

	reg[31:0] pcInputAddr; //type 'reg' for test
	wire[31:0] pcOutAddr;
	wire[31:0] imOutData;
	wire[8:0] ctrlUnitOutCode;

	wire[31:0] reg1Data;
	wire[31:0] reg2Data;
	wire[4:0] writeReg;
	wire[31:0] extSign32;//符号扩展单元
	wire[31:0] mw32Out;
	wire[3:0] aluctrl;//alu的控制信号
	wire[31:0] aluResult;//ALU运算结果
	wire[31:0] dmOutData;

	reg regWrite;//for test
	wire[31:0] writeData;//for test

/*	//to test DM read
	reg[31:0] dmAddr;
	wire[31:0] dmData;
	reg dmRead;
	reg dmWrite;
*/	
	//to test RegHeap
	reg[4:0] readReg1_t,readReg2_t;
	wire[31:0] reg1Data_t,reg2Data_t;
	reg writeReg_t;

	initial
	begin
/*	//to test DM read
		dmAddr=7;
		dmRead=1;
		dmWrite=1;
*/
		//to test RegHeap
		$dumpfile("test1.vcd");
		$dumpvars;
		readReg1_t=9;
		writeReg_t=1;

		clk=0;
		regWrite=0;
		pcInputAddr=0;
		#20 pcInputAddr=1;
		#20 pcInputAddr=2;
		#20 pcInputAddr=3;
		#40 $finish;
	end

	always 
	 #10 clk<=~clk;

	PC pc(.inAddr(pcInputAddr),.outAddr(pcOutAddr),.clk(clk));
	IM im(.inAddr(pcOutAddr),.outContent(imOutData));//imOutData为读出的指令
	controlUnit controlunit(.inCode(imOutData[31:26]),.outCode(ctrlUnitOutCode));
	muxtwo_4 mw4(.in1(imOutData[20:16]),.in2(imOutData[15:11]),.sl(ctrlUnitOutCode[8]),.out(writeReg));//
	RegHeap regHeap(.readReg1(imOutData[25:21]),.readReg2(imOutData[20:16]),.writeReg(writeReg),.regWrite(ctrlUnitOutCode[5]),.writeData(writeData),.reg1Data(reg1Data),.reg2Data(reg2Data),.clk(clk));
	signExt signext(.in1(imOutData[15:0]),.out(extSign32));
	muxtwo_32 mw32(.in1(reg2Data),.in2(extSign32),.sl(ctrlUnitOutCode[7]),.out(mw32Out));
	ALUControl aluControl(.func(imOutData[5:0]),.aluop(ctrlUnitOutCode[1:0]),.aluctrl(aluctrl),.clk(clk));
	ALU alu(.in1(reg1Data),.in2(mw32Out),.ctrl(aluctrl),.out(aluResult));
	DM dm(.inAddr(aluResult),.writeData(reg2Data),.memRead(ctrlUnitOutCode[4]),.memWrite(ctrlUnitOutCode[3]),.outData(dmOutData),.clk(clk));
	muxtwo_32 mw32_2(.in1(aluResult),.in2(dmOutData),.sl(ctrlUnitOutCode[6]),.out(writeData));
endmodule

test1.vcd
$date
	Mon May 16 22:10:30 2016
$end
$version
	Icarus Verilog
$end
$timescale
	1s
$end
$scope module testBench $end
$var wire 32 ! aluResult [31:0] $end
$var wire 4 " aluctrl [3:0] $end
$var wire 9 # ctrlUnitOutCode [8:0] $end
$var wire 32 $ dmOutData [31:0] $end
$var wire 32 % extSign32 [31:0] $end
$var wire 32 & imOutData [31:0] $end
$var wire 32 ' mw32Out [31:0] $end
$var wire 32 ( pcOutAddr [31:0] $end
$var wire 32 ) reg1Data [31:0] $end
$var wire 32 * reg2Data [31:0] $end
$var wire 32 + writeData [31:0] $end
$var wire 5 , writeReg [4:0] $end
$var reg 1 - clk $end
$var reg 32 . pcInputAddr [31:0] $end
$var reg 5 / readReg1_t [4:0] $end
$var reg 1 0 regWrite $end
$var reg 1 1 writeReg_t $end
$scope module pc $end
$var wire 1 2 clk $end
$var wire 32 3 inAddr [31:0] $end
$var reg 32 4 con [31:0] $end
$var reg 32 5 outAddr [31:0] $end
$upscope $end
$scope module im $end
$var wire 32 6 inAddr [31:0] $end
$var wire 32 7 outContent [31:0] $end
$upscope $end
$scope module controlunit $end
$var wire 1 8 clk $end
$var wire 6 9 inCode [5:0] $end
$var wire 9 : outCode [8:0] $end
$var reg 9 ; result [8:0] $end
$upscope $end
$scope module mw4 $end
$var wire 5 < in1 [4:0] $end
$var wire 5 = in2 [4:0] $end
$var wire 5 > out [4:0] $end
$var wire 1 ? sl $end
$upscope $end
$scope module regHeap $end
$var wire 1 2 clk $end
$var wire 5 @ readReg1 [4:0] $end
$var wire 5 A readReg2 [4:0] $end
$var wire 32 B reg1Data [31:0] $end
$var wire 32 C reg2Data [31:0] $end
$var wire 1 D regWrite $end
$var wire 32 E writeData [31:0] $end
$var wire 5 F writeReg [4:0] $end
$upscope $end
$scope module signext $end
$var wire 16 G in1 [15:0] $end
$var wire 32 H out [31:0] $end
$var wire 16 I temp [15:0] $end
$upscope $end
$scope module mw32 $end
$var wire 32 J in1 [31:0] $end
$var wire 32 K in2 [31:0] $end
$var wire 32 L out [31:0] $end
$var wire 1 M sl $end
$upscope $end
$scope module aluControl $end
$var wire 2 N aluop [1:0] $end
$var wire 1 2 clk $end
$var wire 6 O func [5:0] $end
$var reg 4 P aluctrl [3:0] $end
$upscope $end
$scope module alu $end
$var wire 1 Q clk $end
$var wire 4 R ctrl [3:0] $end
$var wire 32 S in1 [31:0] $end
$var wire 32 T in2 [31:0] $end
$var wire 32 U out [31:0] $end
$var reg 32 V result [31:0] $end
$upscope $end
$scope module dm $end
$var wire 1 2 clk $end
$var wire 32 W inAddr [31:0] $end
$var wire 1 X memRead $end
$var wire 1 Y memWrite $end
$var wire 32 Z outData [31:0] $end
$var wire 32 [ writeData [31:0] $end
$upscope $end
$scope module mw32_2 $end
$var wire 32 \ in1 [31:0] $end
$var wire 32 ] in2 [31:0] $end
$var wire 32 ^ out [31:0] $end
$var wire 1 _ sl $end
$upscope $end
$upscope $end
$enddefinitions $end
#0
$dumpvars
0_
b0 ^
b0 ]
b0 \
bx [
b0 Z
0Y
0X
b0 W
b0 V
b0 U
bx T
bx S
bx R
zQ
bx P
bx O
b0 N
0M
bx L
bx K
bx J
bx I
bx H
bx G
bx F
b0 E
0D
bx C
bx B
bx A
bx @
0?
bx >
bx =
bx <
b0 ;
b0 :
bx 9
z8
bx 7
bx 6
bx 5
b0 4
b0 3
02
11
00
b1001 /
b0 .
0-
bx ,
b0 +
bx *
bx )
bx (
bx '
bx &
bx %
b0 $
b0 #
bx "
b0 !
$end
#10
b111 $
b111 Z
b111 ]
1_
1X
1M
1D
b111 +
b111 E
b111 ^
b11110000 ;
b11110000 #
b11110000 :
b10 V
b10 !
b10 U
b10 W
b10 \
b0 I
b1 '
b1 L
b1 T
b1001 ,
b1001 >
b1001 F
b1 O
b1 G
b1 %
b1 H
b1 K
b1001 A
b10 *
b10 C
b10 J
b10 [
b1000 @
b1 )
b1 B
b1 S
b0 =
b1001 <
b100011 9
b0 5
b10001101000010010000000000000001 &
b10001101000010010000000000000001 7
b0 (
b0 6
b10 P
b10 "
b10 R
1-
12
#20
0-
02
b1 .
b1 3
#30
b10 +
b10 E
b10 ^
b0 $
b0 Z
b0 ]
0_
1Y
0X
0D
b10001000 ;
b10001000 #
b10001000 :
b101011 9
b111 *
b111 C
b111 J
b111 [
b1 5
b10101101000010010000000000000001 &
b10101101000010010000000000000001 7
b1 (
b1 6
1-
12
#40
0-
02
b10 .
b10 3
#50
b111 +
b111 E
b111 ^
b111 $
b111 Z
b111 ]
1_
0Y
1X
1D
b11110000 ;
b11110000 #
b11110000 :
b1010 ,
b1010 >
b1010 F
b1010 A
b10 *
b10 C
b10 J
b10 [
b1010 <
b100011 9
b10 5
b10001101000010100000000000000001 &
b10001101000010100000000000000001 7
b10 (
b10 6
1-
12
#60
0-
02
b11 .
b11 3
#70
b1110 +
b1110 E
b1110 ^
b1011 ,
b1011 >
b1011 F
b0 $
b0 Z
b0 ]
0_
0X
b10 N
0M
1?
b1110 V
b1110 !
b1110 U
b1110 W
b1110 \
b100100010 ;
b100100010 #
b100100010 :
b111 '
b111 L
b111 T
b100000 O
b101100000100000 G
b101100000100000 %
b101100000100000 H
b101100000100000 K
b1010 @
b111 )
b111 B
b111 S
b1011 =
b0 9
b111 *
b111 C
b111 J
b111 [
b11 5
b1010010100101100000100000 &
b1010010100101100000100000 7
b11 (
b11 6
1-
12
