ALU.v
module ALU(in1,in2,ctrl,out,clk);
  input[31:0] in1;
  input[31:0] in2;
  input[3:0] ctrl;
  input clk;
  reg[31:0] result;
  output[31:0] out;
  
  initial
  begin
    result=0;
  end
  
  
  always @(posedge clk)
  begin
    case(ctrl)
    4'b0000:  result<=in1&in2;
    4'b0001:  result<=in1||in2;
    4'b0010:  result<=in1+in2;
    4'b0110:  result<=in1-in2;
    4'b0111:  result<=(in1<in2)?1:0;
    4'b1100:  result<=!(in1||in2);
    default:  result<=0;
  endcase
  end
  
  assign out=result;
  
  
endmodule

ALUControl.v
module ALUControl(func,aluop,aluctrl,clk);
	input[5:0] func;
	input[1:0] aluop;
	input clk;
	output[3:0] aluctrl;

	reg[3:0] aluctrl;

	always @(posedge clk) begin
		if(aluop==2'b00)
			aluctrl<=4'b0010;
		else if(aluop==2'b01)
			aluctrl<=4'b0110;
		else if(aluop==2'b10)
			begin
				case(func)
					6'b100000: aluctrl<=4'b0010;
					6'b100010: aluctrl<=4'b0110;
					6'b100100: aluctrl<=4'b0000;
					6'b100101: aluctrl<=4'b0001;
					6'b101010: aluctrl<=4'b0111;
					default: aluctrl<=4'b0000;
				endcase
			end
		else 
			aluctrl<=0;
	end

endmodule

muxtwo_32.v
//32???????
module muxtwo_32(in1,in2,sl,out);
  input[31:0] in1;
  input[31:0] in2;  
  input sl;   //????????
  output[31:0] out;
  
  assign out=(sl==0)?in1:in2;
  
endmodule

signExt.v
module signExt(in1,out);
	input[15:0] in1;
	output[31:0] out;
	wire[15:0] temp;

	assign temp=in1[15]==0?16'h0000:16'hffff;
	assign out ={temp[15:0],in1[15:0]} ;


endmodule

RegHeap.v
module RegHeap(readReg1,readReg2,writeReg,regWrite,writeData,reg1Data,reg2Data,clk);
  input[4:0] readReg1;
  input[4:0] readReg2;
  input[4:0] writeReg;//
  input regWrite;//
  input[31:0] writeData;
  input clk;
  output[31:0] reg1Data;
  output[31:0] reg2Data;
  
  reg[31:0] mem[31:0];//????

  initial
  begin
    $readmemh("regHeapData.data",mem);
  end
  
  always @(posedge clk)
  begin
    if(regWrite)mem[writeReg]<=writeData;  
  end
  
   assign reg1Data=mem[readReg1];
   assign reg2Data=mem[readReg2];
  
endmodule

muxtwo_4.v
//????????????????????????????????????
module muxtwo_4(in1,in2,sl,out);
  input[4:0] in1;
  input[4:0] in2;  
  input sl;   //
  output[4:0] out;
  
  assign out=(sl==0)?in1:in2;
  
endmodule

controlUnit.v
module controlUnit(inCode,outCode,clk);
	input[5:0] inCode;
	input clk;
	output[8:0] outCode; 
	reg[8:0] result; 
//0011100000
	always @(posedge clk)
	begin
		case(inCode)
			6'b000000: result<=9'b100100010;
			6'b100011: result<=9'b011110000;
			6'b101011: result<=9'b010001000;
			6'b000100: result<=9'b000000101;
			default: result<=9'b000000000;
		endcase
	end

	assign outCode = result;

endmodule

IM.v
module IM #(parameter WIDTH=32)(inAddr,outContent);
  reg[WIDTH-1:0] mem[255:0];//256?32?????????????
  input[WIDTH-1:0] inAddr;//????????
  output[WIDTH-1:0] outContent;//??????
  reg[WIDTH-1:0] content;
  
  integer i;
  
  initial
  begin
    $readmemh("memData.data",mem);
    for(i=0;i<8;i=i+1)
      $display(mem[i]);
  end
  assign outContent=mem[inAddr];
  
  
endmodule

PC.v
module PC #(parameter WIDTH=32) (inAddr,outAddr,clk);
  input[WIDTH-1:0] inAddr;
  output[WIDTH-1:0] outAddr;
  reg[WIDTH-1:0] outAddr;
  input clk;
  reg[WIDTH-1:0] con;

  
  initial
  begin
    con<=0;
  end
  
  always @(posedge clk)
  begin
    outAddr<=inAddr;
  end
  
  //assign outAddr=con;
endmodule

testBench.v
`include"PC.v"
`include"IM.v"
`include"controlUnit.v"
`include"RegHeap.v"
`include"muxtwo_4.v"
`include"signExt.v"
`include"muxtwo_32.v"
`include"ALUControl.v"
`include"ALU.v"
module testBench();
	reg clk;

	reg[31:0] pcInputAddr; //type 'reg' for test
	wire[31:0] pcOutAddr;
	wire[31:0] imOutData;
	wire[8:0] ctrlUnitOutCode;

	wire[31:0] reg1Data;
	wire[31:0] reg2Data;
	wire[4:0] writeReg;
	wire[31:0] extSign32;//符号扩展单元
	wire[31:0] mw32Out;
	wire[3:0] aluctrl;//alu的控制信号
	wire[31:0] aluResult;//ALU运算结果

	reg regWrite;//for test
	reg[31:0] writeData;//for test

	

	initial
	begin
		
		clk=0;
		regWrite=0;
		writeData=6;
		pcInputAddr=0;
		$dumpfile("test1.vcd");
		$dumpvars;
		#10 pcInputAddr=0;
		#10 pcInputAddr=1;
		#10 pcInputAddr=2;
		#10 pcInputAddr=3;
		#10 pcInputAddr=5;
		#10 $finish;
	end

	always 
	 #1 clk<=~clk;

	PC pc(.inAddr(pcInputAddr),.outAddr(pcOutAddr),.clk(clk));
	IM im(.inAddr(pcOutAddr),.outContent(imOutData));//imOutData为读出的指令
	controlUnit controlunit(.inCode(imOutData[31:26]),.outCode(ctrlUnitOutCode),.clk(clk));
	muxtwo_4 mw4(.in1(imOutData[20:16]),.in2(imOutData[15:11]),.sl(ctrlUnitOutCode[8]),.out(writeReg));//
	RegHeap regHeap(.readReg1(imOutData[25:21]),.readReg2(imOutData[20:16]),.writeReg(writeReg),.regWrite(regWrite),.writeData(writeData),.reg1Data(reg1Data),.reg2Data(reg2Data),.clk(clk));
	signExt signext(.in1(imOutData[15:0]),.out(extSign32));
	muxtwo_32 mw32(.in1(reg2Data),.in2(extSign32),.sl(ctrlUnitOutCode[7]),.out(mw32Out));
	ALUControl aluControl(.func(imOutData[5:0]),.aluop(ctrlUnitOutCode[1:0]),.aluctrl(aluctrl),.clk(clk));
	ALU alu(.in1(reg1Data),.in2(mw32Out),.ctrl(aluctrl),.out(aluResult),.clk(clk));
endmodule

test1.vcd
$date
	Mon May 16 19:16:02 2016
$end
$version
	Icarus Verilog
$end
$timescale
	1s
$end
$scope module testBench $end
$var wire 32 ! aluResult [31:0] $end
$var wire 4 " aluctrl [3:0] $end
$var wire 9 # ctrlUnitOutCode [8:0] $end
$var wire 32 $ extSign32 [31:0] $end
$var wire 32 % imOutData [31:0] $end
$var wire 32 & mw32Out [31:0] $end
$var wire 32 ' pcOutAddr [31:0] $end
$var wire 32 ( reg1Data [31:0] $end
$var wire 32 ) reg2Data [31:0] $end
$var wire 5 * writeReg [4:0] $end
$var reg 1 + clk $end
$var reg 32 , pcInputAddr [31:0] $end
$var reg 1 - regWrite $end
$var reg 32 . writeData [31:0] $end
$scope module pc $end
$var wire 1 / clk $end
$var wire 32 0 inAddr [31:0] $end
$var reg 32 1 con [31:0] $end
$var reg 32 2 outAddr [31:0] $end
$upscope $end
$scope module im $end
$var wire 32 3 inAddr [31:0] $end
$var wire 32 4 outContent [31:0] $end
$var integer 32 5 i [31:0] $end
$upscope $end
$scope module controlunit $end
$var wire 1 / clk $end
$var wire 6 6 inCode [5:0] $end
$var wire 9 7 outCode [8:0] $end
$var reg 9 8 result [8:0] $end
$upscope $end
$scope module mw4 $end
$var wire 5 9 in1 [4:0] $end
$var wire 5 : in2 [4:0] $end
$var wire 5 ; out [4:0] $end
$var wire 1 < sl $end
$upscope $end
$scope module regHeap $end
$var wire 1 / clk $end
$var wire 5 = readReg1 [4:0] $end
$var wire 5 > readReg2 [4:0] $end
$var wire 32 ? reg1Data [31:0] $end
$var wire 32 @ reg2Data [31:0] $end
$var wire 1 A regWrite $end
$var wire 32 B writeData [31:0] $end
$var wire 5 C writeReg [4:0] $end
$upscope $end
$scope module signext $end
$var wire 16 D in1 [15:0] $end
$var wire 32 E out [31:0] $end
$var wire 16 F temp [15:0] $end
$upscope $end
$scope module mw32 $end
$var wire 32 G in1 [31:0] $end
$var wire 32 H in2 [31:0] $end
$var wire 32 I out [31:0] $end
$var wire 1 J sl $end
$upscope $end
$scope module aluControl $end
$var wire 2 K aluop [1:0] $end
$var wire 1 / clk $end
$var wire 6 L func [5:0] $end
$var reg 4 M aluctrl [3:0] $end
$upscope $end
$scope module alu $end
$var wire 1 / clk $end
$var wire 4 N ctrl [3:0] $end
$var wire 32 O in1 [31:0] $end
$var wire 32 P in2 [31:0] $end
$var wire 32 Q out [31:0] $end
$var reg 32 R result [31:0] $end
$upscope $end
$upscope $end
$enddefinitions $end
#0
$dumpvars
b0 R
b0 Q
bx P
bx O
bx N
bx M
bx L
bx K
xJ
bx I
bx H
bx G
bx F
bx E
bx D
bx C
b110 B
0A
bx @
bx ?
bx >
bx =
x<
bx ;
bx :
bx 9
bx 8
bx 7
bx 6
b1000 5
bx 4
bx 3
bx 2
b0 1
b0 0
0/
b110 .
0-
b0 ,
0+
bx *
bx )
bx (
bx '
bx &
bx %
bx $
bx #
bx "
b0 !
$end
#1
b1111111111111111 F
b11 &
b11 I
b11 P
b1011 *
b1011 ;
b1011 C
b100000 L
b1111100000100000 D
b11111111111111111111100000100000 $
b11111111111111111111100000100000 E
b11111111111111111111100000100000 H
b1011 >
b11 )
b11 @
b11 G
b1010 =
b100 (
b100 ?
b100 O
b11111 :
b1011 9
b0 6
b0 K
0J
0<
b0 2
b1010010111111100000100000 %
b1010010111111100000100000 4
b0 '
b0 3
b0 8
b0 #
b0 7
b0 M
b0 "
b0 N
1+
1/
#2
0+
0/
#3
b11111 *
b11111 ;
b11111 C
b10 K
1<
b10 M
b10 "
b10 N
b100100010 8
b100100010 #
b100100010 7
1+
1/
#4
0+
0/
#5
b111 R
b111 !
b111 Q
1+
1/
#6
0+
0/
#7
1+
1/
#8
0+
0/
#9
1+
1/
#10
0+
0/
#11
1+
1/
#12
0+
0/
#13
1+
1/
#14
0+
0/
#15
1+
1/
#16
0+
0/
#17
1+
1/
#18
0+
0/
#19
1+
1/
#20
0+
0/
b1 ,
b1 0
#21
b0 F
b1001 *
b1001 ;
b1001 C
b100010 L
b100100000100010 D
b100100000100010 $
b100100000100010 E
b100100000100010 H
b1001 :
b1 2
b1010010110100100000100010 %
b1010010110100100000100010 4
b1 '
b1 3
1+
1/
#22
0+
0/
#23
b110 M
b110 "
b110 N
1+
1/
#24
0+
0/
#25
b1 R
b1 !
b1 Q
1+
1/
#26
0+
0/
#27
1+
1/
#28
0+
0/
#29
1+
1/
#30
0+
0/
b10 ,
b10 0
#31
b0 &
b0 I
b0 P
b0 *
b0 ;
b0 C
b11 L
b11 D
b11 $
b11 E
b11 H
b0 >
b0 )
b0 @
b0 G
b0 =
b0 (
b0 ?
b0 O
b0 :
b0 9
b101011 6
b10 2
b10101100000000000000000000000011 %
b10101100000000000000000000000011 4
b10 '
b10 3
1+
1/
#32
0+
0/
#33
b11 &
b11 I
b11 P
b0 K
1J
0<
b10001000 8
b10001000 #
b10001000 7
b0 M
b0 "
b0 N
b0 R
b0 !
b0 Q
1+
1/
#34
0+
0/
#35
b10 M
b10 "
b10 N
1+
1/
#36
0+
0/
#37
b11 R
b11 !
b11 Q
1+
1/
#38
0+
0/
#39
1+
1/
#40
0+
0/
b11 ,
b11 0
#41
b101 &
b101 I
b101 P
b101 L
b101 D
b101 $
b101 E
b101 H
b100 6
b11 2
b10000000000000000000000000101 %
b10000000000000000000000000101 4
b11 '
b11 3
1+
1/
#42
0+
0/
#43
b0 &
b0 I
b0 P
b1 K
0J
b101 R
b101 !
b101 Q
b101 8
b101 #
b101 7
1+
1/
#44
0+
0/
#45
b110 M
b110 "
b110 N
b0 R
b0 !
b0 Q
1+
1/
#46
0+
0/
#47
1+
1/
#48
0+
0/
#49
1+
1/
#50
0+
0/
b101 ,
b101 0
#51
b1001 L
b1001 D
b1001 $
b1001 E
b1001 H
b0 6
b101 2
b1001 %
b1001 4
b101 '
b101 3
1+
1/
#52
0+
0/
#53
b10 K
1<
b100100010 8
b100100010 #
b100100010 7
1+
1/
#54
0+
0/
#55
b0 M
b0 "
b0 N
1+
1/
