muxtwo_32.v
//32???????
module muxtwo_32(in1,in2,sl,out);
  input[31:0] in1;
  input[31:0] in2;  
  input sl;   //????????
  output[31:0] out;
  
  assign out=(sl==0)?in1:in2;
  
endmodule

DM.v
module DM(inAddr,writeData,memRead,memWrite,outData,clk);
	input[31:0] inAddr;
	input[31:0] writeData;
	input memRead;
	input memWrite;
	output[31:0] outData;
	input clk;

	reg[31:0] mem[255:0];

	initial begin
		$readmemh("DMData.data",mem);
	end

	always @(posedge clk) begin
		if(memWrite)mem[inAddr]=writeData;
		else;
	end

	assign outData = (memRead==1)?mem[inAddr]:0;

endmodule

ALU.v
module ALU(in1,in2,ctrl,out,clk);
  input[31:0] in1;
  input[31:0] in2;
  input[3:0] ctrl;
  input clk;
  reg[31:0] result;
  output[31:0] out;
  
  initial
  begin
    result=0;
  end
  
  
  always @(posedge clk)
  begin
    case(ctrl)
    4'b0000:  result<=in1&in2;
    4'b0001:  result<=in1||in2;
    4'b0010:  result<=in1+in2;
    4'b0110:  result<=in1-in2;
    4'b0111:  result<=(in1<in2)?1:0;
    4'b1100:  result<=!(in1||in2);
    default:  result<=0;
  endcase
  end
  
  assign out=result;
  
  
endmodule

ALUControl.v
module ALUControl(func,aluop,aluctrl,clk);
	input[5:0] func;
	input[1:0] aluop;
	input clk;
	output[3:0] aluctrl;

	reg[3:0] aluctrl;

	always @(posedge clk) begin
		if(aluop==2'b00)
			aluctrl<=4'b0010;
		else if(aluop==2'b01)
			aluctrl<=4'b0110;
		else if(aluop==2'b10)
			begin
				case(func)
					6'b100000: aluctrl<=4'b0010;
					6'b100010: aluctrl<=4'b0110;
					6'b100100: aluctrl<=4'b0000;
					6'b100101: aluctrl<=4'b0001;
					6'b101010: aluctrl<=4'b0111;
					default: aluctrl<=4'b0000;
				endcase
			end
		else 
			aluctrl<=0;
	end

endmodule

signExt.v
module signExt(in1,out);
	input[15:0] in1;
	output[31:0] out;
	wire[15:0] temp;

	assign temp=in1[15]==0?16'h0000:16'hffff;
	assign out ={temp[15:0],in1[15:0]} ;


endmodule

RegHeap.v
module RegHeap(readReg1,readReg2,writeReg,regWrite,writeData,reg1Data,reg2Data,clk);
  input[4:0] readReg1;
  input[4:0] readReg2;
  input[4:0] writeReg;//
  input regWrite;//
  input[31:0] writeData;
  input clk;
  output[31:0] reg1Data;
  output[31:0] reg2Data;
  
  reg[31:0] mem[31:0];//????

  initial
  begin
    $readmemh("regHeapData.data",mem);
  end
  
  always @(posedge clk or writeData)
  begin
    if(regWrite)mem[writeReg]<=writeData;  
  end
  
   assign reg1Data=mem[readReg1];
   assign reg2Data=mem[readReg2];
  
endmodule

muxtwo_4.v
//????????????????????????????????????
module muxtwo_4(in1,in2,sl,out);
  input[4:0] in1;
  input[4:0] in2;  
  input sl;   //
  output[4:0] out;
  
  assign out=(sl==0)?in1:in2;
  
endmodule

controlUnit.v
module controlUnit(inCode,outCode);
	input[5:0] inCode;
	input clk;
	output[8:0] outCode; 
	reg[8:0] result; 
//0011100000
	always @(inCode)
	begin
		case(inCode)
			6'b000000: result<=9'b100100010;
			6'b100011: result<=9'b011110000;
			6'b101011: result<=9'b010001000;
			6'b000100: result<=9'b000000101;
			default: result<=9'b000000000;
		endcase
	end

	assign outCode = result;

endmodule

IM.v
module IM #(parameter WIDTH=32)(inAddr,outContent);
  reg[WIDTH-1:0] mem[255:0];//256?32?????????????
  input[WIDTH-1:0] inAddr;//????????
  output[WIDTH-1:0] outContent;//??????
  reg[WIDTH-1:0] content;
  
  integer i;
  
  initial
  begin
    $readmemh("IMData.data",mem);
  end
  assign outContent=mem[inAddr];
  
  
endmodule

PC.v
module PC #(parameter WIDTH=32) (inAddr,outAddr,clk);
  input[WIDTH-1:0] inAddr;
  output[WIDTH-1:0] outAddr;
  reg[WIDTH-1:0] outAddr;
  input clk;
  reg[WIDTH-1:0] con;

  
  initial
  begin
    con<=0;
  end
  
  always @(posedge clk)
  begin
    outAddr<=inAddr;
  end
  
  //assign outAddr=con;
endmodule

testBench.v
`include"PC.v"
`include"IM.v"
`include"controlUnit.v"
`include"RegHeap.v"
`include"muxtwo_4.v"
`include"signExt.v"
`include"muxtwo_32.v"
`include"ALUControl.v"
`include"ALU.v"
`include"DM.v"
module testBench();
	reg clk;

	reg[31:0] pcInputAddr; //type 'reg' for test
	wire[31:0] pcOutAddr;
	wire[31:0] imOutData;
	wire[8:0] ctrlUnitOutCode;

	wire[31:0] reg1Data;
	wire[31:0] reg2Data;
	wire[4:0] writeReg;
	wire[31:0] extSign32;//符号扩展单元
	wire[31:0] mw32Out;
	wire[3:0] aluctrl;//alu的控制信号
	wire[31:0] aluResult;//ALU运算结果
	wire[31:0] dmOutData;

	reg regWrite;//for test
	wire[31:0] writeData;//for test

/*	//to test DM read
	reg[31:0] dmAddr;
	wire[31:0] dmData;
	reg dmRead;
	reg dmWrite;
*/	
	//to test RegHeap
	reg[4:0] readReg1_t,readReg2_t;
	wire[31:0] reg1Data_t,reg2Data_t;
	reg writeReg_t;

	initial
	begin
/*	//to test DM read
		dmAddr=7;
		dmRead=1;
		dmWrite=1;
*/
		//to test RegHeap
		$dumpfile("test1.vcd");
		$dumpvars;
		readReg1_t=9;
		writeReg_t=1;

		clk=0;
		regWrite=0;
		pcInputAddr=0;
		#10 pcInputAddr=1;
		#10 pcInputAddr=2;
		#30 $finish;
	end

	always 
	 #1 clk<=~clk;

	PC pc(.inAddr(pcInputAddr),.outAddr(pcOutAddr),.clk(clk));
	IM im(.inAddr(pcOutAddr),.outContent(imOutData));//imOutData为读出的指令
	controlUnit controlunit(.inCode(imOutData[31:26]),.outCode(ctrlUnitOutCode),.clk(clk));
	muxtwo_4 mw4(.in1(imOutData[20:16]),.in2(imOutData[15:11]),.sl(ctrlUnitOutCode[8]),.out(writeReg));//
	RegHeap regHeap(.readReg1(imOutData[25:21]),.readReg2(imOutData[20:16]),.writeReg(writeReg),.regWrite(ctrlUnitOutCode[5]),.writeData(writeData),.reg1Data(reg1Data),.reg2Data(reg2Data),.clk(clk));
	signExt signext(.in1(imOutData[15:0]),.out(extSign32));
	muxtwo_32 mw32(.in1(reg2Data),.in2(extSign32),.sl(ctrlUnitOutCode[7]),.out(mw32Out));
	ALUControl aluControl(.func(imOutData[5:0]),.aluop(ctrlUnitOutCode[1:0]),.aluctrl(aluctrl),.clk(clk));
	ALU alu(.in1(reg1Data),.in2(mw32Out),.ctrl(aluctrl),.out(aluResult),.clk(clk));
	DM dm(.inAddr(aluResult),.writeData(reg2Data),.memRead(ctrlUnitOutCode[4]),.memWrite(ctrlUnitOutCode[3]),.outData(dmOutData),.clk(clk));
	muxtwo_32 mw32_2(.in1(aluResult),.in2(dmOutData),.sl(ctrlUnitOutCode[6]),.out(writeData));
endmodule

test1.vcd
$date
	Mon May 16 20:56:46 2016
$end
$version
	Icarus Verilog
$end
$timescale
	1s
$end
$scope module testBench $end
$var wire 32 ! aluResult [31:0] $end
$var wire 4 " aluctrl [3:0] $end
$var wire 9 # ctrlUnitOutCode [8:0] $end
$var wire 32 $ dmOutData [31:0] $end
$var wire 32 % extSign32 [31:0] $end
$var wire 32 & imOutData [31:0] $end
$var wire 32 ' mw32Out [31:0] $end
$var wire 32 ( pcOutAddr [31:0] $end
$var wire 32 ) reg1Data [31:0] $end
$var wire 32 * reg2Data [31:0] $end
$var wire 32 + writeData [31:0] $end
$var wire 5 , writeReg [4:0] $end
$var reg 1 - clk $end
$var reg 32 . pcInputAddr [31:0] $end
$var reg 5 / readReg1_t [4:0] $end
$var reg 1 0 regWrite $end
$var reg 1 1 writeReg_t $end
$scope module pc $end
$var wire 1 2 clk $end
$var wire 32 3 inAddr [31:0] $end
$var reg 32 4 con [31:0] $end
$var reg 32 5 outAddr [31:0] $end
$upscope $end
$scope module im $end
$var wire 32 6 inAddr [31:0] $end
$var wire 32 7 outContent [31:0] $end
$upscope $end
$scope module controlunit $end
$var wire 1 2 clk $end
$var wire 6 8 inCode [5:0] $end
$var wire 9 9 outCode [8:0] $end
$var reg 9 : result [8:0] $end
$upscope $end
$scope module mw4 $end
$var wire 5 ; in1 [4:0] $end
$var wire 5 < in2 [4:0] $end
$var wire 5 = out [4:0] $end
$var wire 1 > sl $end
$upscope $end
$scope module regHeap $end
$var wire 1 2 clk $end
$var wire 5 ? readReg1 [4:0] $end
$var wire 5 @ readReg2 [4:0] $end
$var wire 32 A reg1Data [31:0] $end
$var wire 32 B reg2Data [31:0] $end
$var wire 1 C regWrite $end
$var wire 32 D writeData [31:0] $end
$var wire 5 E writeReg [4:0] $end
$upscope $end
$scope module signext $end
$var wire 16 F in1 [15:0] $end
$var wire 32 G out [31:0] $end
$var wire 16 H temp [15:0] $end
$upscope $end
$scope module mw32 $end
$var wire 32 I in1 [31:0] $end
$var wire 32 J in2 [31:0] $end
$var wire 32 K out [31:0] $end
$var wire 1 L sl $end
$upscope $end
$scope module aluControl $end
$var wire 2 M aluop [1:0] $end
$var wire 1 2 clk $end
$var wire 6 N func [5:0] $end
$var reg 4 O aluctrl [3:0] $end
$upscope $end
$scope module alu $end
$var wire 1 2 clk $end
$var wire 4 P ctrl [3:0] $end
$var wire 32 Q in1 [31:0] $end
$var wire 32 R in2 [31:0] $end
$var wire 32 S out [31:0] $end
$var reg 32 T result [31:0] $end
$upscope $end
$scope module dm $end
$var wire 1 2 clk $end
$var wire 32 U inAddr [31:0] $end
$var wire 1 V memRead $end
$var wire 1 W memWrite $end
$var wire 32 X outData [31:0] $end
$var wire 32 Y writeData [31:0] $end
$upscope $end
$scope module mw32_2 $end
$var wire 32 Z in1 [31:0] $end
$var wire 32 [ in2 [31:0] $end
$var wire 32 \ out [31:0] $end
$var wire 1 ] sl $end
$upscope $end
$upscope $end
$enddefinitions $end
#0
$dumpvars
x]
b0x \
b0x [
b0 Z
bx Y
b0x X
xW
xV
b0 U
b0 T
b0 S
bx R
bx Q
bx P
bx O
bx N
bx M
xL
bx K
bx J
bx I
bx H
bx G
bx F
bx E
b0x D
xC
bx B
bx A
bx @
bx ?
x>
bx =
bx <
bx ;
bx :
bx 9
bx 8
bx 7
bx 6
bx 5
b0 4
b0 3
02
11
00
b1001 /
b0 .
0-
bx ,
b0x +
bx *
bx )
bx (
bx '
bx &
bx %
b0x $
bx #
bx "
b0 !
$end
#1
b0 H
b0 +
b0 D
b0 \
b0 $
b0 X
b0 [
b10 '
b10 K
b10 R
b1001 ,
b1001 =
b1001 E
b1 N
b1 F
b1 %
b1 G
b1 J
b1001 @
b10 *
b10 B
b10 I
b10 Y
b1010 ?
b10 )
b10 A
b10 Q
b0 <
b1001 ;
b100011 8
0]
0W
0V
b0 M
0L
0C
0>
b0 5
b10001101010010010000000000000001 &
b10001101010010010000000000000001 7
b0 (
b0 6
b0 :
b0 #
b0 9
b0 O
b0 "
b0 P
1-
12
#2
0-
02
#3
b11 +
b11 D
b11 \
b11 $
b11 X
b11 [
b1 '
b1 K
b1 R
1]
1V
1L
1C
b10 T
b10 !
b10 S
b10 U
b10 Z
b10 O
b10 "
b10 P
b11110000 :
b11110000 #
b11110000 9
1-
12
#4
0-
02
#5
b101 +
b101 D
b101 \
b101 $
b101 X
b101 [
b11 *
b11 B
b11 I
b11 Y
b11 T
b11 !
b11 S
b11 U
b11 Z
1-
12
#6
0-
02
#7
b101 *
b101 B
b101 I
b101 Y
1-
12
#8
0-
02
#9
1-
12
#10
0-
02
b1 .
b1 3
#11
b110000000100000 '
b110000000100000 K
b110000000100000 R
b100000 N
b110000000100000 F
b110000000100000 %
b110000000100000 G
b110000000100000 J
b1001 ?
b101 )
b101 A
b101 Q
b1100 <
b0 8
b1 5
b1001010010110000000100000 &
b1001010010110000000100000 7
b1 (
b1 6
1-
12
#12
0-
02
#13
b101 '
b101 K
b101 R
b1100 ,
b1100 =
b1100 E
b110000000100101 +
b110000000100101 D
b110000000100101 \
0]
0V
b10 M
0L
1>
b0 $
b0 X
b0 [
b100100010 :
b100100010 #
b100100010 9
b110000000100101 T
b110000000100101 !
b110000000100101 S
b110000000100101 U
b110000000100101 Z
1-
12
#14
0-
02
#15
b1010 +
b1010 D
b1010 \
b1010 T
b1010 !
b1010 S
b1010 U
b1010 Z
1-
12
#16
0-
02
#17
1-
12
#18
0-
02
#19
1-
12
#20
0-
02
b10 .
b10 3
#21
b1111111111111111 H
b11 '
b11 K
b11 R
b11111 ,
b11111 =
b11111 E
b1111100000100000 F
b11111111111111111111100000100000 %
b11111111111111111111100000100000 G
b11111111111111111111100000100000 J
b1011 @
b11 *
b11 B
b11 I
b11 Y
b1010 ?
b10 )
b10 A
b10 Q
b11111 <
b1011 ;
b10 5
b1010010111111100000100000 &
b1010010111111100000100000 7
b10 (
b10 6
1-
12
#22
0-
02
#23
b101 +
b101 D
b101 \
b101 T
b101 !
b101 S
b101 U
b101 Z
1-
12
